cn_stock_holidays/__init__.py
cn_stock_holidays/common.py
cn_stock_holidays/data.py
cn_stock_holidays/data.txt
cn_stock_holidays/data_hk.py
cn_stock_holidays/data_hk.txt
cn_stock_holidays/meta_functions.py
cn_stock_holidays/wind_holidays.py
cn_stock_holidays/tools/__init__.py
cn_stock_holidays/tools/cmd.py
cn_stock_holidays/tools/remove_weekend_from_day_list.py
cn_stock_holidays/zipline/__init__.py
cn_stock_holidays/zipline/default_calendar.py
cn_stock_holidays/zipline/exchange_calendar_hkex.py
cn_stock_holidays/zipline/exchange_calendar_shsz.py
tests/__init__.py
tests/data_hk_test.py
tests/data_test.py
cn_stock_holidays_pro-1.8.dist-info/LICENSE
cn_stock_holidays_pro-1.8.dist-info/METADATA
cn_stock_holidays_pro-1.8.dist-info/WHEEL
cn_stock_holidays_pro-1.8.dist-info/entry_points.txt
cn_stock_holidays_pro-1.8.dist-info/top_level.txt
cn_stock_holidays_pro-1.8.dist-info/RECORD
